anylabeling/__init__.py
anylabeling/app.py
anylabeling/app_info.py
anylabeling/checks.py
anylabeling/config.py
anylabeling/test.py
anylabeling/utils.py
anylabeling/configs/__init__.py
anylabeling/configs/xanylabeling_config.yaml
anylabeling/configs/__pycache__/__init__.cpython-312.pyc
anylabeling/configs/auto_labeling/__init__.py
anylabeling/configs/auto_labeling/ch_ppocr_v4.yaml
anylabeling/configs/auto_labeling/clrnet_tusimple_r18.yaml
anylabeling/configs/auto_labeling/damo_yolo_l.yaml
anylabeling/configs/auto_labeling/damo_yolo_m.yaml
anylabeling/configs/auto_labeling/damo_yolo_s.yaml
anylabeling/configs/auto_labeling/damo_yolo_t.yaml
anylabeling/configs/auto_labeling/depth_anything_v2_vit_b.yaml
anylabeling/configs/auto_labeling/depth_anything_v2_vit_l.yaml
anylabeling/configs/auto_labeling/depth_anything_v2_vit_s.yaml
anylabeling/configs/auto_labeling/depth_anything_vit_b.yaml
anylabeling/configs/auto_labeling/depth_anything_vit_l.yaml
anylabeling/configs/auto_labeling/depth_anything_vit_s.yaml
anylabeling/configs/auto_labeling/edge_sam.yaml
anylabeling/configs/auto_labeling/edge_sam_with_chinese_clip.yaml
anylabeling/configs/auto_labeling/efficientvit_sam_l0_vit_h.yaml
anylabeling/configs/auto_labeling/efficientvit_sam_l1_vit_h.yaml
anylabeling/configs/auto_labeling/gold_yolo_l.yaml
anylabeling/configs/auto_labeling/gold_yolo_m.yaml
anylabeling/configs/auto_labeling/gold_yolo_n.yaml
anylabeling/configs/auto_labeling/gold_yolo_s.yaml
anylabeling/configs/auto_labeling/groundingdino_swinb_attn_fuse_sam_hq_vit_l_quant.yaml
anylabeling/configs/auto_labeling/groundingdino_swinb_cogcoor_quant.yaml
anylabeling/configs/auto_labeling/groundingdino_swint_ogc_quant.yaml
anylabeling/configs/auto_labeling/groundingdino_swint_sam2_large.yaml
anylabeling/configs/auto_labeling/internimage_l_22kto1k_384.yaml
anylabeling/configs/auto_labeling/japan_ppocr.yaml
anylabeling/configs/auto_labeling/lvm_sam_ssk_buid_vit_b.yaml
x_anylabeling-2.4.2.dist-info/LICENSE
x_anylabeling-2.4.2.dist-info/METADATA
x_anylabeling-2.4.2.dist-info/WHEEL
x_anylabeling-2.4.2.dist-info/entry_points.txt
x_anylabeling-2.4.2.dist-info/top_level.txt
x_anylabeling-2.4.2.dist-info/RECORD
