Metadata-Version: 2.2
Name: x-anylabeling
Version: 2.4.2
Summary: Advanced Auto Labeling Solution with Added Features
Home-page: https://github.com/CVHub520/X-AnyLabeling
Author: CVHub
Author-email: cvhub.cn@gmail.com
License: GPLv3
Keywords: Image Annotation,Machine Learning,Deep Learning
Classifier: Intended Audience :: Developers
Classifier: Intended Audience :: Science/Research
Classifier: Natural Language :: English
Classifier: Operating System :: OS Independent
Classifier: Programming Language :: Python
Classifier: Programming Language :: Python :: 3 :: Only
Requires-Python: >=3.8.0
License-File: LICENSE
Requires-Dist: imgviz>=0.11
Requires-Dist: natsort>=7.1.0
Requires-Dist: numpy<=1.26.4
Requires-Dist: Pillow>=2.8
Requires-Dist: PyYAML
Requires-Dist: termcolor
Requires-Dist: opencv-python-headless
Requires-Dist: PyQt5>=5.15.7; platform_system != "Darwin"
Requires-Dist: onnx==1.13.1
Requires-Dist: qimage2ndarray==1.10.0
Requires-Dist: lapx==0.5.5
Requires-Dist: darkdetect==0.8.0
Requires-Dist: tqdm
Requires-Dist: scipy
Requires-Dist: shapely
Requires-Dist: pyclipper
Requires-Dist: filterpy
Requires-Dist: tokenizers
Requires-Dist: jsonlines
Requires-Dist: onnxruntime==1.16.0
Dynamic: author
Dynamic: author-email
Dynamic: classifier
Dynamic: description
Dynamic: description-content-type
Dynamic: home-page
Dynamic: keywords
Dynamic: license
Dynamic: requires-dist
Dynamic: requires-python
Dynamic: summary
